quasildr/__init__.py
quasildr/graphdr.py
quasildr/structdr.py
quasildr/utils.py
quasildr/version.py
quasildr/external/__init__.py
quasildr/external/neighbors/__init__.py
quasildr/external/neighbors/umap/__init__.py
quasildr/external/neighbors/umap/distances.py
quasildr/external/neighbors/umap/sparse.py
quasildr/external/neighbors/umap/umap_.py
quasildr/external/neighbors/umap/utils.py
quasildr-0.2.2.data/scripts/run_graphdr.py
quasildr-0.2.2.data/scripts/run_structdr.py
quasildr-0.2.2.dist-info/LICENSE
quasildr-0.2.2.dist-info/METADATA
quasildr-0.2.2.dist-info/WHEEL
quasildr-0.2.2.dist-info/top_level.txt
quasildr-0.2.2.dist-info/RECORD
