Metadata-Version: 2.1
Name: quasildr
Version: 0.2.2
Summary: quasilinear representation methods for single-cellomics data
Home-page: https://github.com/jzthree/quasildr
License: UNKNOWN
Download-URL: https://github.com/jzthree/quasildr/archive/v0.2.2.tar.gz
Platform: UNKNOWN
Classifier: Programming Language :: Python :: 3
Classifier: License :: OSI Approved :: BSD License
Classifier: Topic :: Scientific/Engineering :: Bio-Informatics
Requires-Dist: docopt
Requires-Dist: multiprocess
Requires-Dist: numpy
Requires-Dist: pandas
Requires-Dist: plotly
Requires-Dist: scikit-learn
Requires-Dist: scipy
Requires-Dist: seaborn
Requires-Dist: statsmodels
Requires-Dist: plotnine
Requires-Dist: pynndescent
Requires-Dist: nmslib
